Task4d/Jiruse_Cedrik_X00165166_d.v
`timescale 1ns/10ps
module full_adder(input A, B, Ci,
                  output S, Co);

  wire [19:0] id_num = 20'd65166;

  assign Co = (~A & B & Ci) |
              (A & ~B & Ci) |
              (A & B & ~Ci) |
              (A & B & Ci);

  assign S = (~A & ~B & Ci) |
             (~A & B & ~Ci) |
             (A & ~B & ~Ci) |
             (A & B & Ci);

endmodule

module full_adder_b(Ain, Bin, Cin, Sout, Cout);

  input [7:0] Ain, Bin;
  input Cin;
  output [7:0] Sout;
  output Cout;

  wire [7:0] carry;

  full_adder fa_a_0(Ain[0], Bin[0], Cin,     Sout[0], carry[0]);
  full_adder fa_a_1(Ain[1], Bin[1], carry[0],Sout[1], carry[1]);
  full_adder fa_a_2(Ain[2], Bin[2], carry[1],Sout[2], carry[2]);
  full_adder fa_a_3(Ain[3], Bin[3], carry[2],Sout[3], carry[3]);
  full_adder fa_a_4(Ain[4], Bin[4], carry[3],Sout[4], carry[4]);
  full_adder fa_a_5(Ain[5], Bin[5], carry[4],Sout[5], carry[5]);
  full_adder fa_a_6(Ain[6], Bin[6], carry[5],Sout[6], carry[6]);
  full_adder fa_a_7(Ain[7], Bin[7], carry[6],Sout[7], Cout);

endmodule

module full_adder_c(input [15:0] xin, yin,
                    input czin,
                    output [15:0] fsum,
                    output fcout);

wire [15:0] sum;
wire [1:0] cout;
wire fcout = cout[1];
wire [15:0] fsum = {sum [15:8], sum [7:0]};

// ca4d
assign {fcout, fsum} = xin + yin + czin;

// full_adder_b fa_b_0(xin[7:0], yin[7:0], czin, sum[7:0], cout[0]);
// full_adder_b fa_b_1(xin[15:8], yin[15:8], cout[0], sum[15:8], cout[1]);

endmodule

module full_adder_c_tb ();

reg [15:0] xin_tb = 16'b0, yin_tb = 16'b0;
reg czin_tb = 1'b0;
wire [15:0] fsum_tb;
wire fcout_tb;

reg [17:0] testNum = 18'b0, errorNumber = 18'b0;
reg [16:0] sum_exp;

event testOutputs;

integer ii = 1, jj = 2, kk = 1;

full_adder_c fa_c_0 (xin_tb, yin_tb, czin_tb, fsum_tb, fcout_tb);

initial begin

  $display($time, "=========================");
  $display($time, "My name is Cedrik Jiruse");
  $display($time, "My ID Number is X00165166");
  $display($time, "=========================");

  $dumpfile("Jiruse_Cedrik_X00165166_wave_values.vcd");
  $dumpvars(-1, full_adder_c_tb);

  //  xin_tb = 16'b0; yin_tb = 16'b0; czin_tb = 1'b0; #10
  //  $display($time,"xin_tb = %d yin_tb = %d czin_tb = %b fsum_tb = %d fcout_tb=%b",xin_tb,yin_tb,czin_tb,fsum_tb,fcout_tb);
  //  #10 xin_tb = 16'd16234; yin_tb = 16'd23410; czin_tb = 1'b1; #10
  //  $display($time,"xin_tb = %d yin_tb = %d czin_tb = %b fsum_tb = %d fcout_tb=%b",xin_tb,yin_tb,czin_tb,fsum_tb,fcout_tb);
  //  #10 xin_tb = 16'd50234; yin_tb = 16'd23410; czin_tb = 1'b1; #10
  //  $display($time,"xin_tb = %d yin_tb = %d czin_tb = %b fsum_tb = %d fcout_tb=%b",xin_tb,yin_tb,czin_tb,fsum_tb,fcout_tb);
  //  #10

  repeat (1000) begin
    xin_tb = $urandom(ii);
    yin_tb = $urandom(jj);
    czin_tb = $urandom(kk);
    #10 ->testOutputs; #10;
  end

    if (errorNumber == 18'b0) begin
      $display($time, " ");
      $display($time, " All Passed ");
      $display($time, "======================");
      $display($time, " Simulation Finishing");
      $display($time, " %d tests passed.", testNum);
      $display($time, "=====================.");

      $stop;
      $finish;
    end
    else begin
      $display($time, " ");
      $display($time, " Some failed ");
      $display($time, "======================");
      $display($time, " Simulation Finishing");
      $display($time, " %d errors detected.", errorNumber);
      $display($time, "=====================.");

      $stop;
      $finish;
    end
  end

  always @(testOutputs) begin
    sum_exp [16:0] = xin_tb + yin_tb + czin_tb;

    if (sum_exp == {fcout_tb, fsum_tb}) begin
      // $display($time, " ");
      // $display($time, " Test = %d", testNum[17:0]);
      // $display($time, " Inputs A, B, C = %d %d %d", Ain_tb, Bin_tb, Cin_tb);
      // $display($time, " Outputs Cout, Sout = %d %d as expected = %d", Cout_tb, Sout_tb, S_exp);
    end
    else begin
      $display($time, " ");
      $display($time, " ERROR");
      $display($time, " Test = %d", testNum[17:0]);
      $display($time, " Inputs A, B, C = %d %d %b", xin_tb, yin_tb, czin_tb);
      $display($time, " Outputs Cout, Sout = %b %d as expected %d", fcout_tb, fsum_tb, sum_exp);
      $display($time, " ");
      errorNumber = errorNumber + 18'b1;
    end

    testNum = testNum + 18'b1;
  end
endmodule

Task4d/Jiruse_Cedrik_X00165166_wave_values.vcd
$date
	Thu Apr 07 18:55:02 2022
$end
$version
	Icarus Verilog
$end
$timescale
	10ps
$end
$scope module full_adder_c_tb $end
$var event 1 ! testOutputs $end
$var wire 1 " fcout_tb $end
$var wire 16 # fsum_tb [15:0] $end
$var reg 1 $ czin_tb $end
$var reg 18 % errorNumber [17:0] $end
$var reg 17 & sum_exp [16:0] $end
$var reg 18 ' testNum [17:0] $end
$var reg 16 ( xin_tb [15:0] $end
$var reg 16 ) yin_tb [15:0] $end
$var integer 32 * ii [31:0] $end
$var integer 32 + jj [31:0] $end
$var integer 32 , kk [31:0] $end
$scope module fa_c_0 $end
$var wire 2 - cout [1:0] $end
$var wire 1 $ czin $end
$var wire 1 " fcout $end
$var wire 16 . fsum [15:0] $end
$var wire 16 / sum [15:0] $end
$var wire 16 0 xin [15:0] $end
$var wire 16 1 yin [15:0] $end
$upscope $end
$upscope $end
$enddefinitions $end
#0
$dumpvars
b1110000000000 1
b111000000000 0
bz /
b10101000000000 .
bz -
b10000110111001110 ,
b100001101110011011 +
b10000110111001110 *
b1110000000000 )
b111000000000 (
b0 '
bx &
b0 %
0$
b10101000000000 #
0"
1!
$end
#1000
b1 '
b10101000000000 &
1!
#2000
1"
b1000000010101001 #
b1000000010101001 .
b11100010110011000001111110111 ,
b1111110001110001 )
b1111110001110001 1
b111000101100011111101000100000 +
b1000010000111000 (
b1000010000111000 0
b11100010110011000001111110111 *
#3000
b10 '
b11000000010101001 &
1!
#4000
b10011001011010 #
b10011001011010 .
b11000011010110010011011111001100 ,
b1110110011010100 )
b1110110011010100 1
b1101010010110001110101110100001 +
b11100110000110 (
b11100110000110 0
b11000011010110010011011111001100 *
#5000
b11 '
b10010011001011010 &
1!
#6000
b1110101110001101 #
b1110101110001101 .
0"
b101110000100110000101001011101 ,
b1101111100110001 )
b1101111100110001 1
b10011000110011001101110011101110 +
b110001011100 (
b110001011100 0
b101110000100110000101001011101 *
#7000
b100 '
b1110101110001101 &
1!
#8000
b101100001110 #
b101100001110 .
b11100111001000110000010101111010 ,
b1101000000 )
b1101000000 1
b10100000001100110000000010010111 +
b11111001110 (
b11111001110 0
b11100111001000110000010101111010 *
#9000
b101 '
b101100001110 &
1!
#10000
b1011110110001000 #
b1011110110001000 .
1$
b11100011110011001001010010110011 ,
b10010111000000 )
b10010111000000 1
b11100000011101100010001111101100 +
b1001011111000111 (
b1001011111000111 0
b11100011110011001001010010110011 *
#11000
b110 '
b1011110110001000 &
1!
#12000
b1110111010001010 #
b1110111010001010 .
0$
b1100011000100110010101001011000 ,
b1100000111000100 )
b1100000111000100 1
b11100010010110011011111111111101 +
b10110011000110 (
b10110011000110 0
b1100011000100110010101001011000 *
#13000
b111 '
b1110111010001010 &
1!
#14000
b1111110000010101 #
b1111110000010101 .
1$
b1111001110101110110000001111001 ,
b1001100100100001 )
b1001100100100001 1
b10010000100110111001011010011010 +
b110001011110011 (
b110001011110011 0
b1111001110101110110000001111001 *
#15000
b1000 '
b1111110000010101 &
1!
#16000
b1101010001010111 #
b1101010001010111 .
b11100001110101110110010111100110 ,
b110110010010011 )
b110110010010011 1
b1001001110101110110101101010011 +
b110011111000011 (
b110011111000011 0
b11100001110101110110010111100110 *
#17000
b1001 '
b1101010001010111 &
1!
#18000
b111001101011010 #
b111001101011010 .
b101111100011110100011100101111 ,
b10101011111010 )
b10101011111010 1
b1111101010001110010100001111000 +
b100100001011111 (
b100100001011111 0
b101111100011110100011100101111 *
#19000
b1010 '
b111001101011010 &
1!
#20000
b1110011101110111 #
b1110011101110111 .
b10100011100010000110001110100100 ,
b1000001000101111 )
b1000001000101111 1
b10111100000011000000000011001 +
b110010101000111 (
b110010101000111 0
b10100011100010000110001110100100 *
#21000
b1011 '
b1110011101110111 &
1!
#22000
b1111110001010110 #
b1111110001010110 .
b1000100111010110001111001010101 ,
b1101101111001100 )
b1101101111001100 1
b11100110010011011101100100000110 +
b10000010001001 (
b10000010001001 0
b1000100111010110001111001010101 *
#23000
b1100 '
b1111110001010110 &
1!
#24000
b1011010011110000 #
b1011010011110000 .
0$
b111111001001101001101100010010 ,
b1100001110010 )
b1100001110010 1
b111001011000100001011111001111 +
b1001110001111110 (
b1001110001111110 0
b111111001001101001101100010010 *
#25000
b1101 '
b1011010011110000 &
1!
#26000
b1010110001010011 #
b1010110001010011 .
1$
b100010110111000001011101101011 ,
b1001010000001101 )
b1001010000001101 1
b110100100011001001111000100 +
b1100001000101 (
b1100001000101 0
b100010110111000001011101101011 *
#27000
b1110 '
b1010110001010011 &
1!
#28000
b111100011010011 #
b111100011010011 .
b101110110110100010111110110000 ,
b100100001110101 )
b100100001110101 1
b111010110110000100011111110101 +
b11000001011101 (
b11000001011101 0
b101110110110100010111110110000 *
#29000
b1111 '
b111100011010011 &
1!
#30000
b11010001010111 #
b11010001010111 .
b11001000110101000001111111110001 ,
b1001011000101 )
b1001011000101 1
b1100010110011100001000000110010 +
b10000110010001 (
b10000110010001 0
b11001000110101000001111111110001 *
#31000
b10000 '
b11010001010111 &
1!
#32000
1"
b101100010111010 #
b101100010111010 .
0$
b10110111011011011101000011111110 ,
b1000010101001100 )
b1000010101001100 1
b10100110000001111000001000001011 +
b1101001101101110 (
b1101001101101110 0
b10110111011011011101000011111110 *
#33000
b10001 '
b10101100010111010 &
1!
#34000
b1111011000111111 #
b1111011000111111 .
0"
1$
b1000111100010110100000101100111 ,
b1011001110101111 )
b1011001110101111 1
b11010111101010001011000111010000 +
b100001010001111 (
b100001010001111 0
b1000111100010110100000101100111 *
#35000
b10010 '
b1111011000111111 &
1!
#36000
b1001001100100101 #
b1001001100100101 .
1"
0$
b10011110001111001001101001111100 ,
b1111010111101001 )
b1111010111101001 1
b11110100111011011111001110010001 +
b1001110100111100 (
b1001110100111100 0
b10011110001111001001101001111100 *
#37000
b10011 '
b11001001100100101 &
1!
#38000
b110110100100000 #
b110110100100000 .
0"
1$
b1100100110111000000000101001101 ,
b110101001010110 )
b110101001010110 1
b101011011110110110100000011110 +
b1011001001 (
b1011001001 0
b1100100110111000000000101001101 *
#39000
b10100 '
b110110100100000 &
1!
#40000
b1101111011100000 #
b1101111011100000 .
1"
b11110001100010101111001110101010 ,
b1110100011111100 )
b1110100011111100 1
b1111110001110011110011000000111 +
b1111010111100011 (
b1111010111100011 0
b11110001100010101111001110101010 *
#41000
b10101 '
b11101111011100000 &
1!
#42000
b101010010110010 #
b101010010110010 .
0$
b1101110010011101100000100100011 ,
b1001000111010110 )
b1001000111010110 1
b11101011000100101000111010011100 +
b1100001011011100 (
b1100001011011100 0
b1101110010011101100000100100011 *
#43000
b10110 '
b10101010010110010 &
1!
#44000
0"
b1001001110100111 #
b1001001110100111 .
b10110000000100111000000001000 ,
b10000101111011 )
b10000101111011 1
b10111101101101100001111011101101 +
b111001000101100 (
b111001000101100 0
b10110000000100111000000001000 *
#45000
b10111 '
b1001001110100111 &
1!
#46000
b1110111011110010 #
b1110111011110010 .
1$
b101111101011000001111001101001 ,
b1100111010010010 )
b1100111010010010 1
b1001001010101011100110011001010 +
b10000001011111 (
b10000001011111 0
b101111101011000001111001101001 *
#47000
b11000 '
b1110111011110010 &
1!
#48000
b1111000111010101 #
b1111000111010101 .
b1000110010001010111100010110 ,
b100000111000011 )
b100000111000011 1
b11100001111001010011111111000011 +
b1011000000010001 (
b1011000000010001 0
b1000110010001010111100010110 *
#49000
b11001 '
b1111000111010101 &
1!
#50000
1"
b100111101100011 #
b100111101100011 .
b11101000101011100101001010011111 ,
b1111100110010001 )
b1111100110010001 1
b11001000100100111111011000101000 +
b101010111010001 (
b101010111010001 0
b11101000101011100101001010011111 *
#51000
b11010 '
b10100111101100011 &
1!
#52000
0"
b110011100110000 #
b110011100110000 .
0$
b10000000011010010011110001010100 ,
b10100000110000 )
b10100000110000 1
b11000001001000010011000001001 +
b11111100000000 (
b11111100000000 0
b10000000011010010011110001010100 *
#53000
b11011 '
b110011100110000 &
1!
#54000
1"
b1000000101110011 #
b1000000101110011 .
1$
b1101000101010011001001101000101 ,
b1110110010100001 )
b1110110010100001 1
b1010000111010011110101000110110 +
b1001010011010001 (
b1001010011010001 0
b1101000101010011001001101000101 *
#55000
b11100 '
b11000000101110011 &
1!
#56000
0"
b1011111100101100 #
b1011111100101100 .
b11111111100010100110111101000010 ,
b100110100101100 )
b100110100101100 1
b10010110011010110100101100111111 +
b111000111111111 (
b111000111111111 0
b11111111100010100110111101000010 *
#57000
b11101 '
b1011111100101100 &
1!
#58000
b1110100010010101 #
b1110100010010101 .
b11000110000110111000111011011 ,
b111011001100011 )
b111011001100011 1
b110001111111000111010001110100 +
b111001000110001 (
b111001000110001 0
b11000110000110111000111011011 *
#59000
b11110 '
b1110100010010101 &
1!
#60000
b111001100000001 #
b111001100000001 .
0$
b110011001001010100101101100000 ,
b10011010011011 )
b10011010011011 1
b1001101100001110010010011100101 +
b100110001100110 (
b100110001100110 0
b110011001001010100101101100000 *
#61000
b11111 '
b111001100000001 &
1!
#62000
b110101001110111 #
b110101001110111 .
b100101000100010011101111100001 ,
b10111000101101 )
b10111000101101 1
b10110111111010010110001100010 +
b11110001001010 (
b11110001001010 0
b100101000100010011101111100001 *
#63000
b100000 '
b110101001110111 &
1!
#64000
b1110101001110110 #
b1110101001110110 .
1$
b11001010101110000110000000101110 ,
b1000011011100000 )
b1000011011100000 1
b1110000010111111000010001111011 +
b110001110010101 (
b110001110010101 0
b11001010101110000110000000101110 *
#65000
b100001 '
b1110101001110110 &
1!
#66000
b1011001011011011 #
b1011001011011011 .
b10010101101010101101011010111 ,
b101011010110101 )
b101011010110101 1
b1011010101100100101010110000000 +
b101110000100101 (
b101110000100101 0
b10010101101010101101011010111 *
#67000
b100010 '
b1011001011011011 &
1!
#68000
b1010001100100001 #
b1010001100100001 .
1"
b10001011101011011010100100101100 ,
b1111100000001001 )
b1111100000001001 1
b100101001011111011110000001 +
b1010101100010111 (
b1010101100010111 0
b10001011101011011010100100101100 *
#69000
b100011 '
b11010001100100001 &
1!
#70000
b111011011100101 #
b111011011100101 .
b1010100110100111011010000111101 ,
b1100000000111011 )
b1100000000111011 1
b11101111110011011111101001110 +
b1011011010101001 (
b1011011010101001 0
b1010100110100111011010000111101 *
#71000
b100100 '
b10111011011100101 &
1!
#72000
0"
b1001011110100010 #
b1001011110100010 .
b1100001111010110110110111011010 ,
b10100011011110 )
b10100011011110 1
b1101111000000110010011101110111 +
b110111011000011 (
b110111011000011 0
b1100001111010110110110111011010 *
#73000
b100101 '
b1001011110100010 &
1!
#74000
b1011001000000011 #
b1011001000000011 .
b11001011111101010000100110010011 ,
b1010011001101011 )
b1010011001101011 1
b110101111111101010010101001100 +
b101110010111 (
b101110010111 0
b11001011111101010000100110010011 *
#75000
b100110 '
b1011001000000011 &
1!
#76000
b101111100111101 #
b101111100111101 .
0$
b11001110010010000010000110111000 ,
b11101110100001 )
b11101110100001 1
b11010000100110110011100111011101 +
b10001110011100 (
b10001110011100 0
b11001110010010000010000110111000 *
#77000
b100111 '
b101111100111101 &
1!
#78000
b1110110001000110 #
b1110110001000110 .
b11111011001100010101100001011001 ,
b1001000001010000 )
b1001000001010000 1
b101000000110101000111011111010 +
b101101111110110 (
b101101111110110 0
b11111011001100010101100001011001 *
#79000
b101000 '
b1110110001000110 &
1!
#80000
b111100000001011 #
b111100000001011 .
b10110010100010001000110 ,
b11001000001011 )
b11001000001011 1
b101100000010011000000110011 +
b100011000000000 (
b100011000000000 0
b10110010100010001000110 *
#81000
b101001 '
b111100000001011 &
1!
#82000
b110110001111000 #
b110110001111000 .
b10100001110010011101000001111 ,
b11000001010000 )
b11000001010000 1
b101000000110010010111111011000 +
b11110000101000 (
b11110000101000 0
b10100001110010011101000001111 *
#83000
b101010 '
b110110001111000 &
1!
#84000
b1000101111001110 #
b1000101111001110 .
1$
b1010011110101010100000100000100 ,
b100100100100110 )
b100100100100110 1
b10010011011100010100011111111001 +
b100001010100111 (
b100001010100111 0
b1010011110101010100000100000100 *
#85000
b101011 '
b1000101111001110 &
1!
#86000
b1000111010100010 #
b1000111010100010 .
0$
b110111000101100100010000110101 ,
b100100000110100 )
b100100000110100 1
b11010010101110100011101100110 +
b100011001101110 (
b100011001101110 0
b110111000101100100010000110101 *
#87000
b101100 '
b1000111010100010 &
1!
#88000
b1010111010100001 #
b1010111010100001 .
1$
b10000010100000000100111101110010 ,
b101110110011011 )
b101110110011011 1
b11001101111010100101101010101111 +
b101000100000101 (
b101000100000101 0
b10000010100000000100111101110010 *
#89000
b101101 '
b1010111010100001 &
1!
#90000
b1110110011110011 #
b1110110011110011 .
0$
b1010100001110100110100001001011 ,
b1000001001001011 )
b1000001001001011 1
b100101111101001000000100100100 +
b110101010101000 (
b110101010101000 0
b1010100001110100110100001001011 *
#91000
b101110 '
b1110110011110011 &
1!
#92000
b1001010001000100 #
b1001010001000100 .
b11010010010111000101001100010000 ,
b11111010100000 )
b11111010100000 1
b1010000011111100011110111010101 +
b101010110100100 (
b101010110100100 0
b11010010010111000101001100010000 *
#93000
b101111 '
b1001010001000100 &
1!
#94000
b1010101100100110 #
b1010101100100110 .
b1110111001101100101001111010001 ,
b101011000111000 )
b101011000111000 1
b11100000100000101010010010010 +
b101010011101110 (
b101010011101110 0
b1110111001101100101001111010001 *
#95000
b110000 '
b1010101100100110 &
1!
#96000
b1110001001011101 #
b1110001001011101 .
1$
b10001100100100111011101101011110 ,
b10010101000011 )
b10010101000011 1
b10100001111100010010001011101011 +
b1011110100011001 (
b1011110100011001 0
b10001100100100111011101101011110 *
#97000
b110001 '
b1110001001011101 &
1!
#98000
1"
b1011100110111011 #
b1011100110111011 .
0$
b11001110001011101101000001000111 ,
b1110011000011111 )
b1110011000011111 1
b1111110010011110010100110000 +
b1101001110011100 (
b1101001110011100 0
b11001110001011101101000001000111 *
#99000
b110010 '
b11011100110111011 &
1!
#100000
b101111000101100 #
b101111000101100 .
b1001100010101110110001111011100 ,
b1111100110010100 )
b1111100110010100 1
b11001010011111111111011101110001 +
b110010010011000 (
b110010010011000 0
b1001100010101110110001111011100 *
#101000
b110011 '
b10101111000101100 &
1!
#102000
b101100101010 #
b101100101010 .
1$
b11110101111010010010001100101101 ,
b1110010100111110 )
b1110010100111110 1
b10011111011110101110001001111110 +
b10010111101011 (
b10010111101011 0
b11110101111010010010001100101101 *
#103000
b110100 '
b10000101100101010 &
1!
#104000
b11111101110110 #
b11111101110110 .
b11100101101001110111010000001010 ,
b1100011110101010 )
b1100011110101010 1
b11010101011001011100010011100111 +
b111011111001011 (
b111011111001011 0
b11100101101001110111010000001010 *
#105000
b110101 '
b10011111101110110 &
1!
#106000
0"
b1101101101011100 #
b1101101101011100 .
0$
b11011100000001100110111000000011 ,
b110100110100100 )
b110100110100100 1
b11010010011001010110011111111100 +
b111000110111000 (
b111000110111000 0
b11011100000001100110111000000011 *
#107000
b110110 '
b1101101101011100 &
1!
#108000
b101001111111000 #
b101001111111000 .
1$
b11110010101111110011111101101000 ,
b1001000010010 )
b1001000010010 1
b1001011110000001000011001101 +
b100000111100101 (
b100000111100101 0
b11110010101111110011111101101000 *
#109000
b110111 '
b101001111111000 &
1!
#110000
b1111000000101111 #
b1111000000101111 .
b1011000110001100000111001001001 ,
b1101111101111101 )
b1101111101111101 1
b10111110110011001101110100101010 +
b1000010110001 (
b1000010110001 0
b1011000110001100000111001001001 *
#111000
b111000 '
b1111000000101111 &
1!
#112000
b110010010000100 #
b110010010000100 .
b110011100111000010010101110110 ,
b11111000011100 )
b11111000011100 1
b1110011100100011110010100011 +
b10011001100111 (
b10011001100111 0
b110011100111000010010101110110 *
#113000
b111001 '
b110010010000100 &
1!
#114000
b1101011000000100 #
b1101011000000100 .
1"
0$
b1100111011001101111110101111111 ,
b1101011100110110 )
b1101011100110110 1
b10011011001100011101010110001000 +
b1111111011001110 (
b1111111011001110 0
b1100111011001101111110101111111 *
#115000
b111010 '
b11101011000000100 &
1!
#116000
b101100101010100 #
b101100101010100 .
1$
b101110101110111000110110100 ,
b1110011101001000 )
b1110011101001000 1
b10100100010001111110010111101001 +
b111001000001011 (
b111001000001011 0
b101110101110111000110110100 *
#117000
b111011 '
b10101100101010100 &
1!
#118000
b10010001010100 #
b10010001010100 .
0$
b10000000000000011000100100101 ,
b1111001000110100 )
b1111001000110100 1
b11010001010001111000010010110 +
b11001000100000 (
b11001000100000 0
b10000000000000011000100100101 *
#119000
b111100 '
b10010010001010100 &
1!
#120000
0"
b1000010111110111 #
b1000010111110111 .
1$
b11110010110011101110100010 ,
b100100111101111 )
b100100111101111 1
b11110111100101100100011000011111 +
b11110000000111 (
b11110000000111 0
b11110010110011101110100010 *
#121000
b111101 '
b1000010111110111 &
1!
#122000
b1011011110000100 #
b1011011110000100 .
1"
0$
b10010111011001111111101010111011 ,
b1011101001010110 )
b1011101001010110 1
b101011000001001011100111010100 +
b1111110100101110 (
b1111110100101110 0
b10010111011001111111101010111011 *
#123000
b111110 '
b11011011110000100 &
1!
#124000
0"
b1101110111010110 #
b1101110111010110 .
1$
b10000000101110100100011011000000 ,
b1001010011010100 )
b1001010011010100 1
b1101010000011001001001011000101 +
b100100100000001 (
b100100100000001 0
b10000000101110100100011011000000 *
#125000
b111111 '
b1101110111010110 &
1!
#126000
b1111001111101000 #
b1111001111101000 .
b11010001100000100110011111000001 ,
b1000101001000100 )
b1000101001000100 1
b100010010010101000100011000010 +
b110100110100011 (
b110100110100011 0
b11010001100000100110011111000001 *
#127000
b1000000 '
b1111001111101000 &
1!
#128000
b100010100100110 #
b100010100100110 .
1"
0$
b11001100011100101110001010001110 ,
b101111110001110 )
b101111110001110 1
b11000111011000110101110101011011 +
b1110010110011000 (
b1110010110011000 0
b11001100011100101110001010001110 *
#129000
b1000001 '
b10100010100100110 &
1!
#130000
b10100000111 #
b10100000111 .
b1110000000011101010000110110111 ,
b110001000100111 )
b110001000100111 1
b10011101010100110000011100000 +
b1010001011100000 (
b1010001011100000 0
b1110000000011101010000110110111 *
#131000
b1000010 '
b10000010100000111 &
1!
#132000
b1100000111000110 #
b1100000111000110 .
1$
b11011101001001100101010001100 ,
b1111010110001110 )
b1111010110001110 1
b11000111001110101111001101100001 +
b1100110000110111 (
b1100110000110111 0
b11011101001001100101010001100 *
#133000
b1000011 '
b11100000111000110 &
1!
#134000
b10001110001111 #
b10001110001111 .
b1001011110010110100111000011101 ,
b1101001011110111 )
b1101001011110111 1
b1111011111100011101000110101110 +
b101000010010111 (
b101000010010111 0
b1001011110010110100111000011101 *
#135000
b1000100 '
b10010001110001111 &
1!
#136000
b1100100101011001 #
b1100100101011001 .
0"
b1010010111000100000011000111010 ,
b1100000010110011 )
b1100000010110011 1
b1011001111110001011111001010111 +
b100010100101 (
b100010100101 0
b1010010111000100000011000111010 *
#137000
b1000101 '
b1100100101011001 &
1!
#138000
b1100101010011000 #
b1100101010011000 .
1"
b11011111100010011110111001110011 ,
b1101100011011000 )
b1101100011011000 1
b1101100001100011101011010101100 +
b1111000110111111 (
b1111000110111111 0
b11011111100010011110111001110011 *
#139000
b1000110 '
b11100101010011000 &
1!
#140000
b110111111100110 #
b110111111100110 .
0$
b11110001000000101100100100011000 ,
b1010010000000100 )
b1010010000000100 1
b10011110111010001110111101 +
b1100101111100010 (
b1100101111100010 0
b11110001000000101100100100011000 *
#141000
b1000111 '
b10110111111100110 &
1!
#142000
b1111110110101010 #
b1111110110101010 .
0"
1$
b11101100100010010100000000111001 ,
b1011100111010000 )
b1011100111010000 1
b11101000000011111011011101011010 +
b100001111011001 (
b100001111011001 0
b11101100100010010100000000111001 *
#143000
b1001000 '
b1111110110101010 &
1!
#144000
b1011101111110100 #
b1011101111110100 .
0$
b10100010011001000101001010100110 ,
b110011010110000 )
b110011010110000 1
b1011000001111110110010100010011 +
b101010101000100 (
b101010101000100 0
b10100010011001000101001010100110 *
#145000
b1001001 '
b1011101111110100 &
1!
#146000
b1000011101111001 #
b1000011101111001 .
1"
b1110101001011101001110011101111 ,
b1110100010001111 )
b1110100010001111 1
b1000111111110001110011100111000 +
b1001111011101010 (
b1001111011101010 0
b1110101001011101001110011101111 *
#147000
b1001010 '
b11000011101111001 &
1!
#148000
0"
b1101000111111100 #
b1101000111111100 .
b11010001001110101100111001100100 ,
b1011010 )
b1011010 1
b101101010001101111111111011001 +
b1101000110100010 (
b1101000110100010 0
b11010001001110101100111001100100 *
#149000
b1001011 '
b1101000111111100 &
1!
#150000
1"
b100010001100111 #
b100010001100111 .
1$
b1010110111101100101101000010101 ,
b1110011110111001 )
b1110011110111001 1
b11011100101100011110010111000110 +
b101110010101101 (
b101110010101101 0
b1010110111101100101101000010101 *
#151000
b1001100 '
b10100010001100111 &
1!
#152000
0"
b100010001010001 #
b100010001010001 .
b1111111111011100011001111010010 ,
b111101010001 )
b111101010001 1
b10101000111001100000110110001111 +
b11010011111111 (
b11010011111111 0
b1111111111011100011001111010010 *
#153000
b1001101 '
b100010001010001 &
1!
#154000
b100110101110100 #
b100110101110100 .
0$
b10111110001100110010100100101011 ,
b10000111111000 )
b10000111111000 1
b11111100011110000001111010000100 +
b10101101111100 (
b10101101111100 0
b10111110001100110010100100101011 *
#155000
b1001110 '
b100110101110100 &
1!
#156000
b100110011101010 #
b100110011101010 .
b10001001110100010011001110000 ,
b10010011001000 )
b10010011001000 1
b1100100010000010010001110110101 +
b10100000100010 (
b10100000100010 0
b10001001110100010011001110000 *
#157000
b1001111 '
b100110011101010 &
1!
#158000
1"
b100010101000001 #
b100010101000001 .
1$
b11100101111101000111011110110001 ,
b1100101101110101 )
b1100101101110101 1
b10111010101011101100100011110010 +
b111100111001011 (
b111100111001011 0
b11100101111101000111011110110001 *
#159000
b1010000 '
b10100010101000001 &
1!
#160000
b101001011100 #
b101001011100 .
b110100010001101010110111110 ,
b11010001001110 )
b11010001001110 1
b100111000111010011001111001011 +
b1101011000001101 (
b1101011000001101 0
b110100010001101010110111110 *
#161000
b1010001 '
b10000101001011100 &
1!
#162000
b1001101000001011 #
b1001101000001011 .
0$
b100001010111100111100100111 ,
b1100101000000011 )
b1100101000000011 1
b1110011101100100010010000 +
b1101000000001000 (
b1101000000001000 0
b100001010111100111100100111 *
#163000
b1010010 '
b11001101000001011 &
1!
#164000
b1100110000110110 #
b1100110000110110 .
1$
b1011111110000001101110100111100 ,
b1110110101110110 )
b1110110101110110 1
b10111011010101011110101101010001 +
b1101111010111111 (
b1101111010111111 0
b1011111110000001101110100111100 *
#165000
b1010011 '
b11100110000110110 &
1!
#166000
0"
b1100010101000100 #
b1100010101000100 .
b1010101111010010011010100001101 ,
b1000111010011000 )
b1000111010011000 1
b1001100000100011000110011011110 +
b11011010101011 (
b11011010101011 0
b1010101111010010011010100001101 *
#167000
b1010100 '
b1100010101000100 &
1!
#168000
b11110001100110 #
b11110001100110 .
0$
b11011000011111100010010001101010 ,
b1010010110110 )
b1010010110110 1
b1011011000100110001001111000111 +
b10011110110000 (
b10011110110000 0
b11011000011111100010010001101010 *
#169000
b1010101 '
b11110001100110 &
1!
#170000
1"
b1000000111000110 #
b1000000111000110 .
b11101001010001101000101011100011 ,
b1111001111110100 )
b1111001111110100 1
b11111010000011101111000101011100 +
b1000110111010010 (
b1000110111010010 0
b11101001010001101000101011100011 *
#171000
b1010110 '
b11000000111000110 &
1!
#172000
b1011011110111101 #
b1011011110111101 .
b11101101011011011011111011001000 ,
b1111010111100011 )
b1111010111100011 1
b11110001100101001111001010101101 +
b1100000111011010 (
b1100000111011010 0
b11101101011011011011111011001000 *
#173000
b1010111 '
b11011011110111101 &
1!
#174000
b1000011010010 #
b1000011010010 .
b1110010010110011110111000101001 ,
b1111111101110 )
b1111111101110 1
b11110111010001100001110110001010 +
b1111000011100100 (
b1111000011100100 0
b1110010010110011110111000101001 *
#175000
b1011000 '
b10001000011010010 &
1!
#176000
b111011110000010 #
b111011110000010 .
b10001010001001100101111010110 ,
b1010101101100000 )
b1010101101100000 1
b10110000001011111010100110000011 +
b1100110000100010 (
b1100110000100010 0
b10001010001001100101111010110 *
#177000
b1011001 '
b10111011110000010 &
1!
#178000
b1000000010010010 #
b1000000010010010 .
0"
b11110010001110001100001011111 ,
b110011001010110 )
b110011001010110 1
b101011010010010110010011101000 +
b1101000111100 (
b1101000111100 0
b11110010001110001100001011111 *
#179000
b1011010 '
b1000000010010010 &
1!
#180000
b1111000101111001 #
b1111000101111001 .
1$
b11110011100010100101011100010100 ,
b1001011110010001 )
b1001011110010001 1
b11001000110011011001010111001001 +
b101100111100111 (
b101100111100111 0
b11110011100010100101011100010100 *
#181000
b1011011 '
b1111000101111001 &
1!
#182000
b1110101001101100 #
b1110101001101100 .
0$
b1100011010001111011111100000101 ,
b10100110100110 )
b10100110100110 1
b11010011000001010010011011110110 +
b1100000011000110 (
b1100000011000110 0
b1100011010001111011111100000101 *
#183000
b1011100 '
b1110101001101100 &
1!
#184000
b1110111010010010 #
b1110111010010010 .
b11100100001011000011100000000010 ,
b1011001011001010 )
b1011001011001010 1
b1100101000100001011000011111111 +
b11101111001000 (
b11101111001000 0
b11100100001011000011100000000010 *
