Task4a/Jiruse_Cedrik_X00165166.v
`timescale 1ns/10ps
module full_adder(input Ain, Bin, Cin,
                  output Sout, Cout);

  wire [19:0] id_num = 20'd65166;

  assign Cout = (~Ain & Bin & Cin) |
                (Ain & ~Bin & Cin) |
                (Ain & Bin & ~Cin) |
                (Ain & Bin & Cin);

  assign Sout = (~Ain & ~Bin & Cin) |
                (~Ain & Bin & ~Cin) |
                (Ain & ~Bin & ~Cin) |
                (Ain & Bin & Cin);

endmodule

`timescale 1ns/10ps
module full_adder_tb();

reg Ain_tb, Bin_tb, Cin_tb;
wire Sout_tb, Cout_tb;
wire Cout_Exp, Sout_Exp;
wire [1:0] expected;

reg [3:0] testNum = 0, errorNumber = 0;

event testOutputs;

assign expected = Ain_tb + Bin_tb + Cin_tb;
assign Cout_Exp = expected[1];
assign Sout_Exp = expected[0];

full_adder fa_inst0(Ain_tb, Bin_tb, Cin_tb, Sout_tb, Cout_tb);

  initial begin
    $display($time, "=========================");
    $display($time, "My name is Cedrik Jiruse");
    $display($time, "My ID Number is X00165166");
    $display($time, "=========================");

    $dumpfile("Jiruse_Cedrik_X00165166_wave_values.vcd");
    $dumpvars(-1, full_adder_tb);

    repeat (8) begin 
      $display($time, " Test %d", testNum);

      {Ain_tb, Bin_tb, Cin_tb} = testNum[2:0]; 
      #10 -> testOutputs;
      #10 testNum = testNum + 1'b1;
      #10

      $display($time, " ");
    end

    if (errorNumber == 4'b0) begin
      $display($time, " All Passed ");
      $display($time, "======================");
      $display($time, " Simulation Finishing");
      $display($time, "%d errors detected.", errorNumber);
      $display($time, "=====================.");

      $stop;
      $finish;
    end
    else begin
      $display($time, " Some failed ");
      $display($time, "======================");
      $display($time, " Simulation Finishing");
      $display($time, "%d errors detected.", errorNumber);
      $display($time, "=====================.");

      $stop;
      $finish;
    end
  end

  always @(testOutputs) begin
    if  ({Cout_tb, Sout_tb} == {Cout_Exp, Sout_Exp}) begin
      $display($time, " Inputs A, B, C = %b", testNum[2:0]);
      $display($time, " Outputs Cout, Sout = %b%b as expected = %b", Cout_tb, Sout_tb, expected);
    end
    else begin
      $display($time, " ERROR");
      $display($time, " Inputs A, B, C = %b", testNum[2:0]);
      $display($time, " Outputs Cout, Sout = %b%b NOT as expected = %b", Cout_tb, Sout_tb, expected);
      errorNumber = errorNumber + 4'b1;
    end
  end
endmodule

Task4a/Jiruse_Cedrik_X00165166_wave_values.vcd
$date
	Wed Mar 30 10:59:21 2022
$end
$version
	Icarus Verilog
$end
$timescale
	10ps
$end
$scope module full_adder_tb $end
$var event 1 ! testOutputs $end
$var wire 2 " expected [1:0] $end
$var wire 1 # Sout_tb $end
$var wire 1 $ Sout_Exp $end
$var wire 1 % Cout_tb $end
$var wire 1 & Cout_Exp $end
$var reg 1 ' Ain_tb $end
$var reg 1 ( Bin_tb $end
$var reg 1 ) Cin_tb $end
$var reg 4 * errorNumber [3:0] $end
$var reg 4 + testNum [3:0] $end
$scope module fa_inst0 $end
$var wire 1 ' Ain $end
$var wire 1 ( Bin $end
$var wire 1 ) Cin $end
$var wire 1 % Cout $end
$var wire 1 # Sout $end
$var wire 20 , id_num [19:0] $end
$upscope $end
$upscope $end
$enddefinitions $end
#0
$dumpvars
b1111111010001110 ,
b0 +
b0 *
0)
0(
0'
0&
0%
0$
0#
b0 "
1!
$end
#1000
1!
#2000
b1 +
#3000
1#
1$
b1 "
1)
#4000
1!
#5000
b10 +
#6000
1(
b1 "
0)
#7000
1!
#8000
b11 +
#9000
0#
1%
1&
0$
b10 "
1)
#10000
1!
#11000
b100 +
#12000
0%
1#
0&
1$
1'
0(
b1 "
0)
#13000
1!
#14000
b101 +
#15000
1%
0#
1&
0$
b10 "
1)
#16000
1!
#17000
b110 +
#18000
0#
1(
b10 "
0)
#19000
1!
#20000
b111 +
#21000
1#
1$
b11 "
1)
#22000
1!
#23000
b1000 +
