Task4b/Jiruse_Cedrik_X00165166_a.v
`timescale 1ns/10ps
module full_adder(input A, B, Ci,
                  output S, Co);

  wire [19:0] id_num = 20'd65166;

  assign Co = (~A & B & Ci) |
                (A & ~B & Ci) |
                (A & B & ~Ci) |
                (A & B & Ci);

  assign S = (~A & ~B & Ci) |
                (~A & B & ~Ci) |
                (A & ~B & ~Ci) |
                (A & B & Ci);

endmodule

Task4b/Jiruse_Cedrik_X00165166_b.v
module full_adder_b(Ain, Bin, Cin, Sout, Cout);

  input [7:0] Ain, Bin;
  input Cin;
  output [7:0] Sout;
  output Cout;

  wire [19:0] id_num = 20'd65166;

  wire [7:0] Sout, carry;
  wire Cout = carry[7];

  full_adder fa_b_0(.A(Ain[0]), .B(Bin[0]), .Ci(Cin),      .S(Sout[0]), .Co(carry[0]));
  full_adder fa_b_1(.A(Ain[1]), .B(Bin[1]), .Ci(carry[0]), .S(Sout[1]), .Co(carry[1]));
  full_adder fa_b_2(.A(Ain[2]), .B(Bin[2]), .Ci(carry[1]), .S(Sout[2]), .Co(carry[2]));
  full_adder fa_b_3(.A(Ain[3]), .B(Bin[3]), .Ci(carry[2]), .S(Sout[3]), .Co(carry[3]));
  full_adder fa_b_4(.A(Ain[4]), .B(Bin[4]), .Ci(carry[3]), .S(Sout[4]), .Co(carry[4]));
  full_adder fa_b_5(.A(Ain[5]), .B(Bin[5]), .Ci(carry[4]), .S(Sout[5]), .Co(carry[5]));
  full_adder fa_b_6(.A(Ain[6]), .B(Bin[6]), .Ci(carry[5]), .S(Sout[6]), .Co(carry[6]));
  full_adder fa_b_7(.A(Ain[7]), .B(Bin[7]), .Ci(carry[6]), .S(Sout[7]), .Co(carry[7]));

endmodule

`timescale 1ns/10ps
module full_adder_b_tb();

reg [7:0] Ain_tb = 8'h0, Bin_tb = 8'h0;
reg Cin_tb = 8'h0;
wire [7:0] Sout_tb;
wire Cout_tb;
wire Cout_Exp, Sout_Exp;
wire [7:0] expected;

reg [17:0] testNum = 0, errorNumber = 0;

event testOutputs;

assign expected = Ain_tb + Bin_tb + Cin_tb;
assign Cout_Exp = expected[1];
assign Sout_Exp = expected[0];

full_adder_b fa_b_inst0(Ain_tb, Bin_tb, Cin_tb, Sout_tb, Cout_tb);

  initial begin
    $display($time, "=========================");
    $display($time, "My name is Cedrik Jiruse");
    $display($time, "My ID Number is X00165166");
    $display($time, "=========================");

    $dumpfile("Jiruse_Cedrik_X00165166_wave_values.vcd");
    $dumpvars(-1, full_adder_b_tb);

    repeat (65536) begin 
      $display($time, " Test %d", testNum);

      {Ain_tb, Bin_tb, Cin_tb} = testNum[17:0]; 
      #5 -> testOutputs;
      #5 testNum = testNum + 8'b1;

      $display($time, " ");
    end

    if (errorNumber == 8'b0) begin
      $display($time, " All Passed ");
      $display($time, "======================");
      $display($time, " Simulation Finishing");
      $display($time, "%d errors detected.", errorNumber);
      $display($time, "=====================.");

      $stop;
      $finish;
    end
    else begin
      $display($time, " Some failed ");
      $display($time, "======================");
      $display($time, " Simulation Finishing");
      $display($time, "%d errors detected.", errorNumber);
      $display($time, "=====================.");

      $stop;
      $finish;
    end
  end

  always @(testOutputs) begin
    if  ({Cout_tb, Sout_tb} == {Cout_Exp, Sout_Exp}) begin
      $display($time, " Inputs A, B, C = %d", testNum[17:0]);
      $display($time, " Outputs Cout, Sout = %d%d as expected = %d", Cout_tb, Sout_tb, expected);
    end
    else begin
      $display($time, " ERROR");
      $display($time, " Inputs A, B, C = %d", testNum[17:0]);
      $display($time, " Outputs Cout, Sout = %d%d NOT as expected = %d", Cout_tb, Sout_tb, expected);
      errorNumber = errorNumber + 8'b1;
    end
  end
endmodule

Task4b/Jiruse_Cedrik_X00165166_wave_values.vcd
$date
	Wed Mar 30 10:47:20 2022
$end
$version
	Icarus Verilog
$end
$timescale
	10ps
$end
$scope module full_adder_b_tb $end
$var event 1 ! testOutputs $end
$var wire 8 " expected [7:0] $end
$var wire 8 # Sout_tb [7:0] $end
$var wire 1 $ Sout_Exp $end
$var wire 1 % Cout_tb $end
$var wire 1 & Cout_Exp $end
$var reg 8 ' Ain_tb [7:0] $end
$var reg 8 ( Bin_tb [7:0] $end
$var reg 1 ) Cin_tb $end
$var reg 18 * errorNumber [17:0] $end
$var reg 18 + testNum [17:0] $end
$scope module fa_b_inst0 $end
$var wire 8 , Ain [7:0] $end
$var wire 8 - Bin [7:0] $end
$var wire 1 ) Cin $end
$var wire 20 . id_num [19:0] $end
$var wire 8 / carry [7:0] $end
$var wire 8 0 Sout [7:0] $end
$var wire 1 % Cout $end
$scope module fa_b_0 $end
$var wire 1 1 A $end
$var wire 1 2 B $end
$var wire 1 ) Ci $end
$var wire 1 3 Co $end
$var wire 1 4 S $end
$var wire 20 5 id_num [19:0] $end
$upscope $end
$scope module fa_b_1 $end
$var wire 1 6 A $end
$var wire 1 7 B $end
$var wire 1 8 Ci $end
$var wire 1 9 Co $end
$var wire 1 : S $end
$var wire 20 ; id_num [19:0] $end
$upscope $end
$scope module fa_b_2 $end
$var wire 1 < A $end
$var wire 1 = B $end
$var wire 1 > Ci $end
$var wire 1 ? Co $end
$var wire 1 @ S $end
$var wire 20 A id_num [19:0] $end
$upscope $end
$scope module fa_b_3 $end
$var wire 1 B A $end
$var wire 1 C B $end
$var wire 1 D Ci $end
$var wire 1 E Co $end
$var wire 1 F S $end
$var wire 20 G id_num [19:0] $end
$upscope $end
$scope module fa_b_4 $end
$var wire 1 H A $end
$var wire 1 I B $end
$var wire 1 J Ci $end
$var wire 1 K Co $end
$var wire 1 L S $end
$var wire 20 M id_num [19:0] $end
$upscope $end
$scope module fa_b_5 $end
$var wire 1 N A $end
$var wire 1 O B $end
$var wire 1 P Ci $end
$var wire 1 Q Co $end
$var wire 1 R S $end
$var wire 20 S id_num [19:0] $end
$upscope $end
$scope module fa_b_6 $end
$var wire 1 T A $end
$var wire 1 U B $end
$var wire 1 V Ci $end
$var wire 1 W Co $end
$var wire 1 X S $end
$var wire 20 Y id_num [19:0] $end
$upscope $end
$scope module fa_b_7 $end
$var wire 1 Z A $end
$var wire 1 [ B $end
$var wire 1 \ Ci $end
$var wire 1 ] Co $end
$var wire 1 ^ S $end
$var wire 20 _ id_num [19:0] $end
$upscope $end
$upscope $end
$upscope $end
$enddefinitions $end
#0
$dumpvars
b1111111010001110 _
0^
0]
0\
0[
0Z
b1111111010001110 Y
0X
0W
0V
0U
0T
b1111111010001110 S
0R
0Q
0P
0O
0N
b1111111010001110 M
0L
0K
0J
0I
0H
b1111111010001110 G
0F
0E
0D
0C
0B
b1111111010001110 A
0@
0?
0>
0=
0<
b1111111010001110 ;
0:
09
08
07
06
b1111111010001110 5
04
03
02
01
b0 0
b0 /
b1111111010001110 .
b0 -
b0 ,
b0 +
b0 *
0)
b0 (
b0 '
0&
0%
0$
b0 #
b0 "
1!
$end
#500
1!
#1000
b1 #
b1 0
14
1$
b1 "
1)
b1 +
#1500
1!
#2000
b1 #
b1 0
14
12
b1 (
b1 -
b1 "
0)
b10 +
#2500
1!
#3000
1:
18
b10 #
b10 0
04
b1 /
13
1&
0$
b10 "
1)
b11 +
#3500
1!
#4000
0@
0>
1:
09
08
b10 #
b10 0
04
b0 /
03
02
17
b10 (
b10 -
b10 "
0)
b100 +
#4500
1!
#5000
b11 #
b11 0
14
1$
b11 "
1)
b101 +
#5500
1!
#6000
b11 #
b11 0
14
12
b11 (
b11 -
b11 "
0)
b110 +
#6500
1!
#7000
1@
1>
0:
19
18
b100 #
b100 0
04
b11 /
13
0&
0$
b100 "
1)
b111 +
#7500
b1 *
1!
#8000
0F
0>
0:
0D
1@
09
0?
08
b100 #
b100 0
04
b0 /
03
02
07
1=
b100 (
b100 -
b100 "
0)
b1000 +
#8500
b10 *
1!
#9000
b101 #
b101 0
14
1$
b101 "
1)
b1001 +
#9500
b11 *
1!
#10000
b101 #
b101 0
14
12
b101 (
b101 -
b101 "
0)
b1010 +
#10500
b100 *
1!
#11000
1:
18
b110 #
b110 0
04
b1 /
13
1&
0$
b110 "
1)
b1011 +
#11500
b101 *
1!
#12000
0F
0D
1@
0?
0>
1:
09
08
b110 #
b110 0
04
b0 /
03
02
17
b110 (
b110 -
b110 "
0)
b1100 +
#12500
b110 *
1!
#13000
b111 #
b111 0
14
1$
b111 "
1)
b1101 +
#13500
b111 *
1!
#14000
b111 #
b111 0
14
12
b111 (
b111 -
b111 "
0)
b1110 +
#14500
b1000 *
1!
#15000
1F
1D
0@
1?
1>
0:
19
18
b1000 #
b1000 0
04
b111 /
13
0&
0$
b1000 "
1)
b1111 +
#15500
b1001 *
1!
#16000
0L
0>
0:
0D
0@
0J
1F
09
0?
0E
08
b1000 #
b1000 0
04
b0 /
03
02
07
0=
1C
b1000 (
b1000 -
b1000 "
0)
b10000 +
#16500
b1010 *
1!
#17000
b1001 #
b1001 0
14
1$
b1001 "
1)
b10001 +
#17500
b1011 *
1!
#18000
b1001 #
b1001 0
14
12
b1001 (
b1001 -
b1001 "
0)
b10010 +
#18500
b1100 *
1!
#19000
1:
18
b1010 #
b1010 0
04
b1 /
13
1&
0$
b1010 "
1)
b10011 +
#19500
b1101 *
1!
#20000
0@
0>
1:
09
08
b1010 #
b1010 0
04
b0 /
03
02
17
b1010 (
b1010 -
b1010 "
0)
b10100 +
#20500
b1110 *
1!
#21000
b1011 #
b1011 0
14
1$
b1011 "
1)
b10101 +
#21500
b1111 *
1!
#22000
b1011 #
b1011 0
14
12
b1011 (
b1011 -
b1011 "
0)
b10110 +
#22500
b10000 *
1!
#23000
1@
1>
0:
19
18
b1100 #
b1100 0
04
b11 /
13
0&
0$
b1100 "
1)
b10111 +
#23500
b10001 *
1!
#24000
0L
0J
1F
0E
0>
0:
0D
1@
09
0?
08
b1100 #
b1100 0
04
b0 /
03
02
07
1=
b1100 (
b1100 -
b1100 "
0)
b11000 +
#24500
b10010 *
1!
#25000
b1101 #
b1101 0
14
1$
b1101 "
1)
b11001 +
#25500
b10011 *
1!
#26000
b1101 #
b1101 0
14
12
b1101 (
b1101 -
b1101 "
0)
b11010 +
#26500
b10100 *
1!
#27000
1:
18
b1110 #
b1110 0
04
b1 /
13
1&
0$
b1110 "
1)
b11011 +
#27500
b10101 *
1!
#28000
0L
0J
1F
0E
0D
1@
0?
0>
1:
09
08
b1110 #
b1110 0
04
b0 /
03
02
17
b1110 (
b1110 -
b1110 "
0)
b11100 +
#28500
b10110 *
1!
#29000
b1111 #
b1111 0
14
1$
b1111 "
1)
b11101 +
#29500
b10111 *
1!
#30000
b1111 #
b1111 0
14
12
b1111 (
b1111 -
b1111 "
0)
b11110 +
#30500
b11000 *
1!
#31000
1L
1J
0F
1E
1D
0@
1?
1>
0:
19
18
b10000 #
b10000 0
04
b1111 /
13
0&
0$
b10000 "
1)
b11111 +
#31500
b11001 *
1!
#32000
0R
0>
0:
0D
0@
0J
0F
0P
1L
09
0?
0E
0K
08
b10000 #
b10000 0
04
b0 /
03
02
07
0=
0C
1I
b10000 (
b10000 -
b10000 "
0)
b100000 +
#32500
b11010 *
1!
#33000
b10001 #
b10001 0
14
1$
b10001 "
1)
b100001 +
#33500
b11011 *
1!
#34000
b10001 #
b10001 0
14
12
b10001 (
b10001 -
b10001 "
0)
b100010 +
#34500
b11100 *
1!
#35000
1:
18
b10010 #
b10010 0
04
b1 /
13
1&
0$
b10010 "
1)
b100011 +
#35500
b11101 *
1!
#36000
0@
0>
1:
09
08
b10010 #
b10010 0
04
b0 /
03
02
17
b10010 (
b10010 -
b10010 "
0)
b100100 +
#36500
b11110 *
1!
#37000
b10011 #
b10011 0
14
1$
b10011 "
1)
b100101 +
#37500
b11111 *
1!
#38000
b10011 #
b10011 0
14
12
b10011 (
b10011 -
b10011 "
0)
b100110 +
#38500
b100000 *
1!
#39000
1@
1>
0:
19
18
b10100 #
b10100 0
04
b11 /
13
0&
0$
b10100 "
1)
b100111 +
#39500
b100001 *
1!
#40000
0F
0>
0:
0D
1@
09
0?
08
b10100 #
b10100 0
04
b0 /
03
02
07
1=
b10100 (
b10100 -
b10100 "
0)
b101000 +
#40500
b100010 *
1!
#41000
b10101 #
b10101 0
14
1$
b10101 "
1)
b101001 +
#41500
b100011 *
1!
#42000
b10101 #
b10101 0
14
12
b10101 (
b10101 -
b10101 "
0)
b101010 +
#42500
b100100 *
1!
#43000
1:
18
b10110 #
b10110 0
04
b1 /
13
1&
0$
b10110 "
1)
b101011 +
#43500
b100101 *
1!
#44000
0F
0D
1@
0?
0>
1:
09
08
b10110 #
b10110 0
04
b0 /
03
02
17
b10110 (
b10110 -
b10110 "
0)
b101100 +
#44500
b100110 *
1!
#45000
b10111 #
b10111 0
14
1$
b10111 "
1)
b101101 +
#45500
b100111 *
1!
#46000
b10111 #
b10111 0
14
12
b10111 (
b10111 -
b10111 "
0)
b101110 +
#46500
b101000 *
1!
#47000
1F
1D
0@
1?
1>
0:
19
18
b11000 #
b11000 0
04
b111 /
13
0&
0$
b11000 "
1)
b101111 +
#47500
b101001 *
1!
#48000
0R
0P
1L
0K
0>
0:
0D
0@
0J
1F
09
0?
0E
08
b11000 #
b11000 0
04
b0 /
03
02
07
0=
1C
b11000 (
b11000 -
b11000 "
0)
b110000 +
#48500
b101010 *
1!
#49000
b11001 #
b11001 0
14
1$
b11001 "
1)
b110001 +
#49500
b101011 *
1!
#50000
b11001 #
b11001 0
14
12
b11001 (
b11001 -
b11001 "
0)
b110010 +
#50500
b101100 *
1!
#51000
1:
18
b11010 #
b11010 0
04
b1 /
13
1&
0$
b11010 "
1)
b110011 +
#51500
b101101 *
1!
#52000
0@
0>
1:
09
08
b11010 #
b11010 0
04
b0 /
03
02
17
b11010 (
b11010 -
b11010 "
0)
b110100 +
#52500
b101110 *
1!
#53000
b11011 #
b11011 0
14
1$
b11011 "
1)
b110101 +
#53500
b101111 *
1!
#54000
b11011 #
b11011 0
14
12
b11011 (
b11011 -
b11011 "
0)
b110110 +
#54500
b110000 *
1!
#55000
1@
1>
0:
19
18
b11100 #
b11100 0
04
b11 /
13
0&
0$
b11100 "
1)
b110111 +
#55500
b110001 *
1!
#56000
0R
0P
1L
0K
0J
1F
0E
0>
0:
0D
1@
09
0?
08
b11100 #
b11100 0
04
b0 /
03
02
07
1=
b11100 (
b11100 -
b11100 "
0)
b111000 +
#56500
b110010 *
1!
#57000
b11101 #
b11101 0
14
1$
b11101 "
1)
b111001 +
#57500
b110011 *
1!
#58000
b11101 #
b11101 0
14
12
b11101 (
b11101 -
b11101 "
0)
b111010 +
#58500
b110100 *
1!
#59000
1:
18
b11110 #
b11110 0
04
b1 /
13
1&
0$
b11110 "
1)
b111011 +
#59500
b110101 *
1!
#60000
0R
0P
1L
0K
0J
1F
0E
0D
1@
0?
0>
1:
09
08
b11110 #
b11110 0
04
b0 /
03
02
17
b11110 (
b11110 -
b11110 "
0)
b111100 +
#60500
b110110 *
1!
#61000
b11111 #
b11111 0
14
1$
b11111 "
1)
b111101 +
#61500
b110111 *
1!
#62000
b11111 #
b11111 0
14
12
b11111 (
b11111 -
b11111 "
0)
b111110 +
#62500
b111000 *
1!
#63000
1R
1P
0L
1K
1J
0F
1E
1D
0@
1?
1>
0:
19
18
b100000 #
b100000 0
04
b11111 /
13
0&
0$
b100000 "
1)
b111111 +
#63500
b111001 *
1!
#64000
0X
0>
0:
0D
0@
0J
0F
0P
0L
0V
1R
09
0?
0E
0K
0Q
08
b100000 #
b100000 0
04
b0 /
03
02
07
0=
0C
0I
1O
b100000 (
b100000 -
b100000 "
0)
b1000000 +
#64500
b111010 *
1!
#65000
b100001 #
b100001 0
14
1$
b100001 "
1)
b1000001 +
#65500
b111011 *
1!
#66000
b100001 #
b100001 0
14
12
b100001 (
b100001 -
b100001 "
0)
b1000010 +
#66500
b111100 *
1!
#67000
1:
18
b100010 #
b100010 0
04
b1 /
13
1&
0$
b100010 "
1)
b1000011 +
#67500
b111101 *
1!
#68000
0@
0>
1:
09
08
b100010 #
b100010 0
04
b0 /
03
02
17
b100010 (
b100010 -
b100010 "
0)
b1000100 +
#68500
b111110 *
1!
#69000
b100011 #
b100011 0
14
1$
b100011 "
1)
b1000101 +
#69500
b111111 *
1!
#70000
b100011 #
b100011 0
14
12
b100011 (
b100011 -
b100011 "
0)
b1000110 +
#70500
b1000000 *
1!
#71000
1@
1>
0:
19
18
b100100 #
b100100 0
04
b11 /
13
0&
0$
b100100 "
1)
b1000111 +
#71500
b1000001 *
1!
#72000
0F
0>
0:
0D
1@
09
0?
08
b100100 #
b100100 0
04
b0 /
03
02
07
1=
b100100 (
b100100 -
b100100 "
0)
b1001000 +
#72500
b1000010 *
1!
#73000
b100101 #
b100101 0
14
1$
b100101 "
1)
b1001001 +
#73500
b1000011 *
1!
#74000
b100101 #
b100101 0
14
12
b100101 (
b100101 -
b100101 "
0)
b1001010 +
#74500
b1000100 *
1!
#75000
1:
18
b100110 #
b100110 0
04
b1 /
13
1&
0$
b100110 "
1)
b1001011 +
#75500
b1000101 *
1!
#76000
0F
0D
1@
0?
0>
1:
09
08
b100110 #
b100110 0
04
b0 /
03
02
17
b100110 (
b100110 -
b100110 "
0)
b1001100 +
#76500
b1000110 *
1!
#77000
b100111 #
b100111 0
14
1$
b100111 "
1)
b1001101 +
#77500
b1000111 *
1!
#78000
b100111 #
b100111 0
14
12
b100111 (
b100111 -
b100111 "
0)
b1001110 +
#78500
b1001000 *
1!
#79000
1F
1D
0@
1?
1>
0:
19
18
b101000 #
b101000 0
04
b111 /
13
0&
0$
b101000 "
1)
b1001111 +
#79500
b1001001 *
1!
#80000
0L
0>
0:
0D
0@
0J
1F
09
0?
0E
08
b101000 #
b101000 0
04
b0 /
03
02
07
0=
1C
b101000 (
b101000 -
b101000 "
0)
b1010000 +
#80500
b1001010 *
1!
#81000
b101001 #
b101001 0
14
1$
b101001 "
1)
b1010001 +
#81500
b1001011 *
1!
#82000
b101001 #
b101001 0
14
12
b101001 (
b101001 -
b101001 "
0)
b1010010 +
#82500
b1001100 *
1!
#83000
1:
18
b101010 #
b101010 0
04
b1 /
13
1&
0$
b101010 "
1)
b1010011 +
#83500
b1001101 *
1!
#84000
0@
0>
1:
09
08
b101010 #
b101010 0
04
b0 /
03
02
17
b101010 (
b101010 -
b101010 "
0)
b1010100 +
#84500
b1001110 *
1!
#85000
b101011 #
b101011 0
14
1$
b101011 "
1)
b1010101 +
#85500
b1001111 *
1!
#86000
b101011 #
b101011 0
14
12
b101011 (
b101011 -
b101011 "
0)
b1010110 +
#86500
b1010000 *
1!
#87000
1@
1>
0:
19
18
b101100 #
b101100 0
04
b11 /
13
0&
0$
b101100 "
1)
b1010111 +
#87500
b1010001 *
1!
#88000
0L
0J
1F
0E
0>
0:
0D
1@
09
0?
08
b101100 #
b101100 0
04
b0 /
03
02
07
1=
b101100 (
b101100 -
b101100 "
0)
b1011000 +
#88500
b1010010 *
1!
#89000
b101101 #
b101101 0
14
1$
b101101 "
1)
b1011001 +
#89500
b1010011 *
1!
#90000
b101101 #
b101101 0
14
12
b101101 (
b101101 -
b101101 "
0)
b1011010 +
#90500
b1010100 *
1!
#91000
1:
18
b101110 #
b101110 0
04
b1 /
13
1&
0$
b101110 "
1)
b1011011 +
#91500
b1010101 *
1!
#92000
0L
0J
1F
0E
0D
1@
0?
0>
1:
09
08
b101110 #
b101110 0
04
b0 /
03
02
17
b101110 (
b101110 -
b101110 "
0)
b1011100 +
#92500
b1010110 *
1!
#93000
b101111 #
b101111 0
14
1$
b101111 "
1)
b1011101 +
#93500
b1010111 *
1!
#94000
b101111 #
b101111 0
14
12
b101111 (
b101111 -
b101111 "
0)
b1011110 +
#94500
b1011000 *
1!
#95000
1L
1J
0F
1E
1D
0@
1?
1>
0:
19
18
b110000 #
b110000 0
04
b1111 /
13
0&
0$
b110000 "
1)
b1011111 +
#95500
b1011001 *
1!
#96000
0X
0V
1R
0Q
0>
0:
0D
0@
0J
0F
0P
1L
09
0?
0E
0K
08
b110000 #
b110000 0
04
b0 /
03
02
07
0=
0C
1I
b110000 (
b110000 -
b110000 "
0)
b1100000 +
#96500
b1011010 *
1!
#97000
b110001 #
b110001 0
14
1$
b110001 "
1)
b1100001 +
#97500
b1011011 *
1!
#98000
b110001 #
b110001 0
14
12
b110001 (
b110001 -
b110001 "
0)
b1100010 +
#98500
b1011100 *
1!
#99000
1:
18
b110010 #
b110010 0
04
b1 /
13
1&
0$
b110010 "
1)
b1100011 +
#99500
b1011101 *
1!
#100000
0@
0>
1:
09
08
b110010 #
b110010 0
04
b0 /
03
02
17
b110010 (
b110010 -
b110010 "
0)
b1100100 +
#100500
b1011110 *
1!
#101000
b110011 #
b110011 0
14
1$
b110011 "
1)
b1100101 +
#101500
b1011111 *
1!
#102000
b110011 #
b110011 0
14
12
b110011 (
b110011 -
b110011 "
0)
b1100110 +
#102500
b1100000 *
1!
#103000
1@
1>
0:
19
18
b110100 #
b110100 0
04
b11 /
13
0&
0$
b110100 "
1)
b1100111 +
#103500
b1100001 *
1!
#104000
0F
0>
0:
0D
1@
09
0?
08
b110100 #
b110100 0
04
b0 /
03
02
07
1=
b110100 (
b110100 -
b110100 "
0)
b1101000 +
#104500
b1100010 *
1!
#105000
b110101 #
b110101 0
14
1$
b110101 "
1)
b1101001 +
#105500
b1100011 *
1!
#106000
b110101 #
b110101 0
14
12
b110101 (
b110101 -
b110101 "
0)
b1101010 +
#106500
b1100100 *
1!
#107000
1:
18
b110110 #
b110110 0
04
b1 /
13
1&
0$
b110110 "
1)
b1101011 +
#107500
b1100101 *
1!
#108000
0F
0D
1@
0?
0>
1:
09
08
b110110 #
b110110 0
04
b0 /
03
02
17
b110110 (
b110110 -
b110110 "
0)
b1101100 +
#108500
b1100110 *
1!
#109000
b110111 #
b110111 0
14
1$
b110111 "
1)
b1101101 +
#109500
b1100111 *
1!
#110000
b110111 #
b110111 0
14
12
b110111 (
b110111 -
b110111 "
0)
b1101110 +
#110500
b1101000 *
1!
#111000
1F
1D
0@
1?
1>
0:
19
18
b111000 #
b111000 0
04
b111 /
13
0&
0$
b111000 "
1)
b1101111 +
#111500
b1101001 *
1!
#112000
0X
0V
1R
0Q
0P
1L
0K
0>
0:
0D
0@
0J
1F
09
0?
0E
08
b111000 #
b111000 0
04
b0 /
03
02
07
0=
1C
b111000 (
b111000 -
b111000 "
0)
b1110000 +
#112500
b1101010 *
1!
#113000
b111001 #
b111001 0
14
1$
b111001 "
1)
b1110001 +
#113500
b1101011 *
1!
#114000
b111001 #
b111001 0
14
12
b111001 (
b111001 -
b111001 "
0)
b1110010 +
#114500
b1101100 *
1!
#115000
1:
18
b111010 #
b111010 0
04
b1 /
13
1&
0$
b111010 "
1)
b1110011 +
#115500
b1101101 *
1!
#116000
0@
0>
1:
09
08
b111010 #
b111010 0
04
b0 /
03
02
17
b111010 (
b111010 -
b111010 "
0)
b1110100 +
#116500
b1101110 *
1!
#117000
b111011 #
b111011 0
14
1$
b111011 "
1)
b1110101 +
#117500
b1101111 *
1!
#118000
b111011 #
b111011 0
14
12
b111011 (
b111011 -
b111011 "
0)
b1110110 +
#118500
b1110000 *
1!
#119000
1@
1>
0:
19
18
b111100 #
b111100 0
04
b11 /
13
0&
0$
b111100 "
1)
b1110111 +
#119500
b1110001 *
1!
#120000
0X
0V
1R
0Q
0P
1L
0K
0J
1F
0E
0>
0:
0D
1@
09
0?
08
b111100 #
b111100 0
04
b0 /
03
02
07
1=
b111100 (
b111100 -
b111100 "
0)
b1111000 +
#120500
b1110010 *
1!
#121000
b111101 #
b111101 0
14
1$
b111101 "
1)
b1111001 +
#121500
b1110011 *
1!
#122000
b111101 #
b111101 0
14
12
b111101 (
b111101 -
b111101 "
0)
b1111010 +
#122500
b1110100 *
1!
#123000
1:
18
b111110 #
b111110 0
04
b1 /
13
1&
0$
b111110 "
1)
b1111011 +
#123500
b1110101 *
1!
#124000
0X
0V
1R
0Q
0P
1L
0K
0J
1F
0E
0D
1@
0?
0>
1:
09
08
b111110 #
b111110 0
04
b0 /
03
02
17
b111110 (
b111110 -
b111110 "
0)
b1111100 +
#124500
b1110110 *
1!
#125000
b111111 #
b111111 0
14
1$
b111111 "
1)
b1111101 +
#125500
b1110111 *
1!
#126000
b111111 #
b111111 0
14
12
b111111 (
b111111 -
b111111 "
0)
b1111110 +
#126500
b1111000 *
1!
#127000
1X
1V
0R
1Q
1P
0L
1K
1J
0F
1E
1D
0@
1?
1>
0:
19
18
b1000000 #
b1000000 0
04
b111111 /
13
0&
0$
b1000000 "
1)
b1111111 +
#127500
b1111001 *
1!
#128000
0^
0>
0:
0D
0@
0J
0F
0P
0L
0V
0R
0\
1X
09
0?
0E
0K
0Q
0W
08
b1000000 #
b1000000 0
04
b0 /
03
02
07
0=
0C
0I
0O
1U
b1000000 (
b1000000 -
b1000000 "
0)
b10000000 +
#128500
b1111010 *
1!
#129000
b1000001 #
b1000001 0
14
1$
b1000001 "
1)
b10000001 +
#129500
b1111011 *
1!
#130000
b1000001 #
b1000001 0
14
12
b1000001 (
b1000001 -
b1000001 "
0)
b10000010 +
#130500
b1111100 *
1!
#131000
1:
18
b1000010 #
b1000010 0
04
b1 /
13
1&
0$
b1000010 "
1)
b10000011 +
#131500
b1111101 *
1!
#132000
0@
0>
1:
09
08
b1000010 #
b1000010 0
04
b0 /
03
02
17
b1000010 (
b1000010 -
b1000010 "
0)
b10000100 +
#132500
b1111110 *
1!
#133000
b1000011 #
b1000011 0
14
1$
b1000011 "
1)
b10000101 +
#133500
b1111111 *
1!
#134000
b1000011 #
b1000011 0
14
12
b1000011 (
b1000011 -
b1000011 "
0)
b10000110 +
#134500
b10000000 *
1!
#135000
1@
1>
0:
19
18
b1000100 #
b1000100 0
04
b11 /
13
0&
0$
b1000100 "
1)
b10000111 +
#135500
b10000001 *
1!
#136000
0F
0>
0:
0D
1@
09
0?
08
b1000100 #
b1000100 0
04
b0 /
03
02
07
1=
b1000100 (
b1000100 -
b1000100 "
0)
b10001000 +
#136500
b10000010 *
1!
#137000
b1000101 #
b1000101 0
14
1$
b1000101 "
1)
b10001001 +
#137500
b10000011 *
1!
#138000
b1000101 #
b1000101 0
14
12
b1000101 (
b1000101 -
b1000101 "
0)
b10001010 +
#138500
b10000100 *
1!
#139000
1:
18
b1000110 #
b1000110 0
04
b1 /
13
1&
0$
b1000110 "
1)
b10001011 +
#139500
b10000101 *
1!
#140000
0F
0D
1@
0?
0>
1:
09
08
b1000110 #
b1000110 0
04
b0 /
03
02
17
b1000110 (
b1000110 -
b1000110 "
0)
b10001100 +
#140500
b10000110 *
1!
#141000
b1000111 #
b1000111 0
14
1$
b1000111 "
1)
b10001101 +
#141500
b10000111 *
1!
#142000
b1000111 #
b1000111 0
14
12
b1000111 (
b1000111 -
b1000111 "
0)
b10001110 +
#142500
b10001000 *
1!
#143000
1F
1D
0@
1?
1>
0:
19
18
b1001000 #
b1001000 0
04
b111 /
13
0&
0$
b1001000 "
1)
b10001111 +
#143500
b10001001 *
1!
#144000
0L
0>
0:
0D
0@
0J
1F
09
0?
0E
08
b1001000 #
b1001000 0
04
b0 /
03
02
07
0=
1C
b1001000 (
b1001000 -
b1001000 "
0)
b10010000 +
#144500
b10001010 *
1!
#145000
b1001001 #
b1001001 0
14
1$
b1001001 "
1)
b10010001 +
#145500
b10001011 *
1!
#146000
b1001001 #
b1001001 0
14
12
b1001001 (
b1001001 -
b1001001 "
0)
b10010010 +
#146500
b10001100 *
1!
#147000
1:
18
b1001010 #
b1001010 0
04
b1 /
13
1&
0$
b1001010 "
1)
b10010011 +
#147500
b10001101 *
1!
#148000
0@
0>
1:
09
08
b1001010 #
b1001010 0
04
b0 /
03
02
17
b1001010 (
b1001010 -
b1001010 "
0)
b10010100 +
#148500
b10001110 *
1!
#149000
b1001011 #
b1001011 0
14
1$
b1001011 "
1)
b10010101 +
#149500
b10001111 *
1!
#150000
b1001011 #
b1001011 0
14
12
b1001011 (
b1001011 -
b1001011 "
0)
b10010110 +
#150500
b10010000 *
1!
#151000
1@
1>
0:
19
18
b1001100 #
b1001100 0
04
b11 /
13
0&
0$
b1001100 "
1)
b10010111 +
#151500
b10010001 *
1!
#152000
0L
0J
1F
0E
0>
0:
0D
1@
09
0?
08
b1001100 #
b1001100 0
04
b0 /
03
02
07
1=
b1001100 (
b1001100 -
b1001100 "
0)
b10011000 +
#152500
b10010010 *
1!
#153000
b1001101 #
b1001101 0
14
1$
b1001101 "
1)
b10011001 +
#153500
b10010011 *
1!
#154000
b1001101 #
b1001101 0
14
12
b1001101 (
b1001101 -
b1001101 "
0)
b10011010 +
#154500
b10010100 *
1!
#155000
1:
18
b1001110 #
b1001110 0
04
b1 /
13
1&
0$
b1001110 "
1)
b10011011 +
#155500
b10010101 *
1!
#156000
0L
0J
1F
0E
0D
1@
0?
0>
1:
09
08
b1001110 #
b1001110 0
04
b0 /
03
02
17
b1001110 (
b1001110 -
b1001110 "
0)
b10011100 +
#156500
b10010110 *
1!
#157000
b1001111 #
b1001111 0
14
1$
b1001111 "
1)
b10011101 +
#157500
b10010111 *
1!
#158000
b1001111 #
b1001111 0
14
12
b1001111 (
b1001111 -
b1001111 "
0)
b10011110 +
#158500
b10011000 *
1!
#159000
1L
1J
0F
1E
1D
0@
1?
1>
0:
19
18
b1010000 #
b1010000 0
04
b1111 /
13
0&
0$
b1010000 "
1)
b10011111 +
#159500
b10011001 *
1!
#160000
0R
0>
0:
0D
0@
0J
0F
0P
1L
09
0?
0E
0K
08
b1010000 #
b1010000 0
04
b0 /
03
02
07
0=
0C
1I
b1010000 (
b1010000 -
b1010000 "
0)
b10100000 +
#160500
b10011010 *
1!
#161000
b1010001 #
b1010001 0
14
1$
b1010001 "
1)
b10100001 +
#161500
b10011011 *
1!
