Task2/ff_with_and.v
`timescale 1ns/1ps

module ff_with_and(
                    input clk, clear0, preset0, ip0, ip1,
                    output op0, op0bar,
                    output [19:0] id_num);

  wire [19:0] id_num = 20'h65166;
  wire d0 = ip0 & ip1;
  wire op0bar = ~op0;

  reg op0;

  always @(posedge clk or negedge clear0 or negedge preset0) begin
    if (clear0 == 1'b0) begin
      op0 <= 1'b0;
    end
    else if (preset0 == 1'b0)
    begin
      op0 <= 1'b1;
    end
    else begin
      op0 <= d0;
    end
  end
endmodule

Task2/ff_with_and_tb.v
`timescale 1ns/1ps

module ff_with_and_tb();
  reg clktb, clear0tb, preset0tb, ip0tb, ip1tb;
  wire op0tb, op0bartb;
  wire [19:0] id_numtb;

  ff_with_and ff_with_and_inst0(clktb,
                                clear0tb,
                                preset0tb,
                                ip0tb,
                                ip1tb,
                                op0tb,
                                op0bartb,
                                id_numtb);

  // clock
  initial begin
    clktb = 1'b1;
    forever #50 clktb = ~clktb;
  end

  // header
  initial begin
    $display($time, "=========================");
    $display($time, "My name is Cedrik Jiruse");
    $display($time, "My ID Number is X00165166");
    $display($time, "=========================");

    $dumpfile("./Task2/ff_with_and_wave_values.vcd");
    $dumpvars(-1, ff_with_and_tb);

    // run to the end of the simulation
    @(posedge clktb); // start of tick1
    @(posedge clktb); // start of tick2
    @(posedge clktb); // start of tick3
    @(posedge clktb); // start of tick4
    @(posedge clktb); // start of tick5
    @(posedge clktb); // start of tick6
    @(posedge clktb); // start of tick7
    @(posedge clktb); // start of tick8
    @(posedge clktb); // start of tick9
    
    $display($time, "..");
    $display($time, ".Simulation finishing.");
    $display($time, "..");

    $stop;
    $finish;
  end

  // preset0 pin
  initial begin
    // start of tick1
    preset0tb = 1'b1;
    // start of tick2
    @(posedge clktb);
    // start of tick3
    @(posedge clktb);
    #25 preset0tb = 1'b0;
    #25 preset0tb = 1'b1;
    // start of tick4
    @(posedge clktb);
    // start of tick5
    @(posedge clktb);
    // start of tick6
    @(posedge clktb);
    // start of tick7
    @(posedge clktb);
    // start of tick8
    @(posedge clktb);
    // start of tick9
    @(posedge clktb);
    #5

    $stop;
    $finish;
  end

  // clear0 pin
  initial begin
    // start of tick1
    clear0tb = 1'b1; #1
    clear0tb = 1'b0;
    #74
    clear0tb = 1'b1;
    // start of tick2
    @(posedge clktb);
    // start of tick3
    @(posedge clktb);
    #50
    clear0tb = 1'b0;
    #25
    clear0tb = 1'b1;
    // start of tick4
    @(posedge clktb);
    // start of tick5
    @(posedge clktb);
    // start of tick6
    @(posedge clktb);
    #25
    clear0tb = 1'b0;
    #50
    clear0tb = 1'b1;
    // start of tick7
    @(posedge clktb);
    // start of tick8
    @(posedge clktb);
    // start of tick9
    @(posedge clktb);
    #5

    $stop;
    $finish;
  end

  // input0 pin
  initial begin
    // start of tick1
    ip0tb = 1'b1; #1
    ip0tb = 1'b0;
    #74
    ip0tb = 1'b1;
    // start of tick2
    @(posedge clktb);
    #25
    ip0tb = 1'b0;
    // start of tick3
    @(posedge clktb);
    #50
    ip0tb = 1'b1;
    #40
    ip0tb = 1'b0;
    // start of tick4
    @(posedge clktb);
    #75
    ip0tb = 1'b1;
    #23
    ip0tb = 1'b0;
    // start of tick5
    @(posedge clktb);
    // start of tick6
    @(posedge clktb);
    #10
    ip0tb = 1'b1;
    #65
    ip0tb = 1'b0;
    #15
    ip0tb = 1'b1;
    // start of tick7
    @(posedge clktb);
    #75
    ip0tb = 1'b0;
    // start of tick8
    @(posedge clktb);
    #25
    ip0tb = 1'b1;
    #50
    ip0tb = 1'b0;
    // start of tick9
    @(posedge clktb);
    #5

    $stop;
    $finish;
  end

  // input1 pin
  initial begin
    // start of tick1
    ip1tb = 1'b1; #1
    ip1tb = 1'b0;
    #74
    ip1tb = 1'b1;
    // start of tick2
    @(posedge clktb);
    // start of tick3
    #25
    ip1tb = 1'b0;
    #50
    ip1tb = 1'b1;
    @(posedge clktb);
    #10
    ip1tb = 1'b0;
    // start of tick4
    @(posedge clktb);
    #25
    ip1tb = 1'b1;
    #23
    ip1tb = 1'b0;
    // start of tick5
    @(posedge clktb);
    #25
    ip1tb = 1'b1;
    #65
    ip1tb = 1'b0;
    // start of tick6
    @(posedge clktb);
    #90
    ip1tb = 1'b1;
    // start of tick7
    @(posedge clktb);
    #75
    ip1tb = 1'b0;
    // start of tick8
    @(posedge clktb);
    #99
    ip1tb = 1'b1;
    // start of tick9
    @(posedge clktb);
    #5

    $stop;
    $finish;
  end
endmodule

Task2/ff_with_and_wave_values.vcd
$date
	Thu Feb 17 17:14:55 2022
$end
$version
	Icarus Verilog
$end
$timescale
	1ps
$end
$scope module ff_with_and_tb $end
$var wire 20 ! id_numtb [19:0] $end
$var wire 1 " op0tb $end
$var wire 1 # op0bartb $end
$var reg 1 $ clear0tb $end
$var reg 1 % clktb $end
$var reg 1 & ip0tb $end
$var reg 1 ' ip1tb $end
$var reg 1 ( preset0tb $end
$scope module ff_with_and_inst0 $end
$var wire 1 $ clear0 $end
$var wire 1 % clk $end
$var wire 1 ) d0 $end
$var wire 20 * id_num [19:0] $end
$var wire 1 & ip0 $end
$var wire 1 ' ip1 $end
$var wire 1 # op0bar $end
$var wire 1 ( preset0 $end
$var reg 1 " op0 $end
$upscope $end
$upscope $end
$enddefinitions $end
#0
$dumpvars
b1100101000101100110 *
1)
1(
1'
1&
1%
1$
0#
1"
b1100101000101100110 !
$end
#1000
1#
0"
0)
0'
0&
0$
#50000
0%
#75000
1)
1'
1&
1$
#100000
0#
1"
1%
#125000
0)
0&
0'
#150000
0%
#175000
1'
#200000
1#
0"
1%
#210000
0'
#225000
0#
1"
0(
#250000
1#
0"
1(
0$
1&
0%
#275000
1$
#290000
0&
#300000
1%
#325000
1'
#348000
0'
#350000
0%
#375000
1&
#398000
0&
#400000
1%
#425000
1'
#450000
0%
#490000
0'
#500000
1%
#510000
1&
#525000
0$
#550000
0%
#575000
1$
0&
#590000
1)
1&
1'
#600000
0#
1"
1%
#650000
0%
#675000
0)
0'
0&
#700000
1#
0"
1%
#725000
1&
#750000
0%
#775000
0&
#799000
1'
